wol_proxy/__init__.py
wol_proxy/app.py
wol_redirect_proxy-1.0.1.dist-info/entry_points.txt
wol_redirect_proxy-1.0.1.dist-info/WHEEL
wol_redirect_proxy-1.0.1.dist-info/METADATA
wol_redirect_proxy-1.0.1.dist-info/RECORD
