Metadata-Version: 2.1
Name: wol-redirect-proxy
Version: 1.0.1
Summary: A simple python Wake-on-LAN proxy
License: MIT
Requires-Python: >=3.8,<4.0
Classifier: License :: OSI Approved :: MIT License
Classifier: Programming Language :: Python :: 3
Classifier: Programming Language :: Python :: 3.8
Classifier: Programming Language :: Python :: 3.9
Classifier: Programming Language :: Python :: 3.10
Classifier: Programming Language :: Python :: 3.11
Requires-Dist: fastapi (>=0.94.1,<0.95.0)
Requires-Dist: ping3 (>=4.0.4,<5.0.0)
Requires-Dist: pyyaml (>=6.0,<7.0)
Requires-Dist: uvicorn (>=0.21.0,<0.22.0)
Requires-Dist: wakeonlan (>=3.0.0,<4.0.0)
